LICENSE
README.md
setup.py
explainable_transformer.egg-info/PKG-INFO
explainable_transformer.egg-info/SOURCES.txt
explainable_transformer.egg-info/dependency_links.txt
explainable_transformer.egg-info/requires.txt
explainable_transformer.egg-info/top_level.txt
explainable_transformers/__init__.py
explainable_transformers/base_explainer.py
explainable_transformers/question_answer.py
explainable_transformers/text_classification.py
explainable_transformers/shap_bugs/__init__.py
explainable_transformers/shap_bugs/_general.py
explainable_transformers/shap_bugs/_waterfall.py
tests/__init__.py
tests/test_model_and_tokenizer.py