Metadata-Version: 2.1
Name: explainable-transformer
Version: 0.2.0
Summary: Software for debugging transformers
Home-page: https://github.com/RohanAwhad/explainable-transformers
Author: Rohan Awhad and Shreya Saxena
Author-email: rohanawhad@gmail.com
License: UNKNOWN
Platform: UNKNOWN
Classifier: Programming Language :: Python :: 3
Classifier: License :: OSI Approved :: MIT License
Classifier: Operating System :: OS Independent
Requires-Python: >=3.7
License-File: LICENSE
